Metadata-Version: 2.4
Name: image_processing_samuell_shoiti
Version: 0.0.1
Summary: Image Processing package using skimage
Home-page: https://github.com/ThePersonWhoLikesUndertale/image-processing-package.git
Author: Samuell Shoiti
Author-email: sppaulisto972@gmail.com
Requires-Python: >=3.8
Requires-Dist: matplotlib
Requires-Dist: numpy
Requires-Dist: scikit-image>=0.16.1
Dynamic: author
Dynamic: author-email
Dynamic: description
Dynamic: description-content-type
Dynamic: home-page
Dynamic: requires-dist
Dynamic: requires-python
Dynamic: summary
